{
  "_source": "eloratings.net",
  "_note": "World Elo Ratings for all 48 FIFA World Cup 2026 qualified nations. Ratings reflect pre-tournament standings (June 2025). Update periodically by running fetch_elo.py.",
  "_updated": "2025-06-01",
  "ratings": {
    "Spain": 2076,
    "France": 2050,
    "England": 2018,
    "Brazil": 2014,
    "Argentina": 2009,
    "Portugal": 1995,
    "Belgium": 1970,
    "Netherlands": 1965,
    "Germany": 1958,
    "Italy": 1950,
    "Colombia": 1900,
    "Uruguay": 1885,
    "Croatia": 1875,
    "Morocco": 1870,
    "Mexico": 1855,
    "Senegal": 1850,
    "United States": 1845,
    "Denmark": 1842,
    "Switzerland": 1838,
    "Austria": 1830,
    "Ecuador": 1820,
    "Japan": 1818,
    "South Korea": 1810,
    "Australia": 1790,
    "Hungary": 1785,
    "Turkey": 1780,
    "Ukraine": 1775,
    "Serbia": 1770,
    "Poland": 1762,
    "Chile": 1755,
    "Venezuela": 1750,
    "Paraguay": 1745,
    "Peru": 1740,
    "Canada": 1738,
    "Costa Rica": 1720,
    "Algeria": 1715,
    "Nigeria": 1710,
    "Cameroon": 1705,
    "Egypt": 1700,
    "Ivory Coast": 1695,
    "Ghana": 1690,
    "Tunisia": 1685,
    "Mali": 1680,
    "Saudi Arabia": 1670,
    "Iran": 1665,
    "Indonesia": 1640,
    "New Zealand": 1620,
    "Jamaica": 1610,
    "Honduras": 1600,
    "Panama": 1598,
    "Guatemala": 1590,
    "Cuba": 1550,
    "Uzbekistan": 1630,
    "Qatar": 1625
  }
}
